README.rst
setup.py
scripts/bmfont2json
scripts/bmfont2json.bat
scripts/dae2json
scripts/dae2json.bat
scripts/effect2json
scripts/effect2json.bat
scripts/exportevents
scripts/exportevents.bat
scripts/json2json
scripts/json2json.bat
scripts/json2stats
scripts/json2stats.bat
scripts/json2tar
scripts/json2tar.bat
scripts/json2txt
scripts/json2txt.bat
scripts/makehtml
scripts/makehtml.bat
scripts/maketzjs
scripts/maketzjs.bat
scripts/material2json
scripts/material2json.bat
scripts/obj2json
scripts/obj2json.bat
scripts/xml2json
scripts/xml2json.bat
turbulenz_tools/__init__.py
turbulenz_tools/version.py
turbulenz_tools.egg-info/PKG-INFO
turbulenz_tools.egg-info/SOURCES.txt
turbulenz_tools.egg-info/dependency_links.txt
turbulenz_tools.egg-info/not-zip-safe
turbulenz_tools.egg-info/requires.txt
turbulenz_tools.egg-info/top_level.txt
turbulenz_tools/tools/__init__.py
turbulenz_tools/tools/appcodegen.py
turbulenz_tools/tools/asset2json.py
turbulenz_tools/tools/bmfont2json.py
turbulenz_tools/tools/dae2json.py
turbulenz_tools/tools/effect2json.py
turbulenz_tools/tools/exportevents.py
turbulenz_tools/tools/json2json.py
turbulenz_tools/tools/json2stats.py
turbulenz_tools/tools/json2tar.py
turbulenz_tools/tools/json2txt.py
turbulenz_tools/tools/makehtml.py
turbulenz_tools/tools/maketzjs.py
turbulenz_tools/tools/material.py
turbulenz_tools/tools/material2json.py
turbulenz_tools/tools/mesh.py
turbulenz_tools/tools/node.py
turbulenz_tools/tools/obj2json.py
turbulenz_tools/tools/pointmap.py
turbulenz_tools/tools/stdtool.py
turbulenz_tools/tools/templates.py
turbulenz_tools/tools/toolsexception.py
turbulenz_tools/tools/vmath.py
turbulenz_tools/tools/xml2json.py
turbulenz_tools/utils/__init__.py
turbulenz_tools/utils/coloured_writer.py
turbulenz_tools/utils/dependencies.py
turbulenz_tools/utils/disassembler.py
turbulenz_tools/utils/hash.py
turbulenz_tools/utils/htmlmin.py
turbulenz_tools/utils/json_stats.py
turbulenz_tools/utils/json_utils.py
turbulenz_tools/utils/profiler.py
turbulenz_tools/utils/subproc.py
turbulenz_tools/utils/xml_json.py