Metadata-Version: 1.1
Name: turbulenz-tools
Version: 1.0.6
Summary: Tools for the creation of games with the Turbulenz Engine
Home-page: https://turbulenz.com/
Author: Turbulenz Limited
Author-email: support@turbulenz.com
License: MIT
Platform: Posix; MacOS X; Windows
Classifier: Development Status :: 5 - Production/Stable
Classifier: Intended Audience :: Developers
Classifier: License :: OSI Approved :: MIT License
Classifier: Operating System :: OS Independent
Classifier: Topic :: Software Development
Classifier: Programming Language :: Python :: 2.7
